{"type":"PR","pr":{"number":308,"head":"317be6617b79a4aaaeed24080a41b716f8bb0ab8"},"user":"596343pepsi","status":"pending_review","branch":"cms/596343pepsi/tbtc-website/news-item-ru/2020-08-15-что-такое-биткойн-utxo","collection":"news-item-ru","commitMessage":"Create News (ru) “2020-08-15-что-такое-биткойн-utxo”","title":"Что такое биткойн UTXO","description":"Что такое биткойн UTXO","objects":{"entry":{"path":"src/pages/news/2020-08-15-что-такое-биткойн-utxo.ru.md","sha":"bc1640f7ab83804432a5adb71e655f308372e595"},"files":[]},"timeStamp":"2020-08-15T18:32:26.989Z","version":"1"}